{
  "$schema": "http://json-schema.org/draft-07/schema#",
  "title": "Contract governs Businessservice",
  "description": "Defines relationship: business.contract governs business.businessservice",
  "allOf": [
    {
      "$ref": "../../base/spec-node-relationship.schema.json"
    }
  ],
  "properties": {
    "id": {
      "const": "business.contract.governs.business.businessservice"
    },
    "source_spec_node_id": {
      "const": "business.contract"
    },
    "source_layer": {
      "const": "business"
    },
    "destination_spec_node_id": {
      "const": "business.businessservice"
    },
    "destination_layer": {
      "const": "business"
    },
    "predicate": {
      "const": "governs"
    },
    "cardinality": {
      "const": "many-to-one"
    },
    "strength": {
      "const": "medium"
    }
  }
}
