{
  "$schema": "http://json-schema.org/draft-07/schema#",
  "title": "ApplicationComponent",
  "description": "Modular, deployable, and replaceable part of a system",
  "allOf": [
    {
      "$ref": "../../base/spec-node.schema.json"
    }
  ],
  "properties": {
    "spec_node_id": {
      "const": "application.applicationcomponent"
    },
    "layer_id": {
      "const": "application"
    },
    "type": {
      "const": "applicationcomponent"
    },
    "attributes": {
      "type": "object",
      "properties": {
        "id": {
          "type": "string",
          "format": "uuid"
        },
        "name": {
          "type": "string"
        },
        "documentation": {
          "type": "string"
        },
        "type": {
          "type": "string"
        },
        "properties": {
          "type": "object",
          "description": "Cross-layer properties"
        }
      },
      "required": [
        "type"
      ],
      "additionalProperties": false
    }
  }
}
