{
  "$schema": "http://json-schema.org/draft-07/schema#",
  "$id": "https://github.com/tinkermonkey/documentation_robotics/spec/nodes/api/oauthflows.node.schema.json",
  "title": "OAuthFlows",
  "description": "Configuration for OAuth 2.0 authentication flows (implicit, password, clientCredentials, authorizationCode), specifying authorization URLs, token URLs, and scopes. Defines OAuth security implementation.",
  "allOf": [
    {
      "$ref": "../../schemas/base/spec-node.schema.json"
    }
  ],
  "properties": {
    "spec_node_id": {
      "const": "api.oauthflows"
    },
    "layer_id": {
      "const": "api"
    },
    "type": {
      "const": "oauthflows"
    },
    "attributes": {
      "type": "object",
      "properties": {
        "id": {
          "type": "string",
          "format": "uuid"
        },
        "name": {
          "type": "string"
        }
      },
      "additionalProperties": false
    }
  }
}
