{
  "id": "ux.experiencestate",
  "layer_id": "ux",
  "name": "ExperienceState",
  "description": "Distinct state that the experience can be in (works across all channels)",
  "attributes": {
    "id": {
      "type": "string",
      "description": "",
      "format": "uuid"
    },
    "name": {
      "type": "string",
      "description": ""
    },
    "initial": {
      "type": "boolean",
      "description": ""
    },
    "description": {
      "type": "string",
      "description": ""
    },
    "channel": {
      "type": "string",
      "description": ""
    },
    "onEnter": {
      "type": "array",
      "description": "Contains relationship"
    },
    "onExit": {
      "type": "array",
      "description": "Contains relationship"
    },
    "transitions": {
      "type": "array",
      "description": "Contains relationship"
    },
    "enabledComponents": {
      "type": "array",
      "description": "Contains relationship"
    },
    "disabledComponents": {
      "type": "array",
      "description": "Contains relationship"
    },
    "hiddenComponents": {
      "type": "array",
      "description": "Contains relationship"
    }
  },
  "required_attributes": [
    "id",
    "name"
  ]
}
